.gitignore
CHANGES.txt
CREDITS.txt
MIT-LICENSE.txt
README.rst
TODO.txt
manual_test.py
setup.py
tox.ini
src/vimpdb/__init__.py
src/vimpdb/bbbconfig.py
src/vimpdb/config.py
src/vimpdb/controller.py
src/vimpdb/debugger.py
src/vimpdb/errors.py
src/vimpdb/proxy.py
src/vimpdb/vimpdb.vim
src/vimpdb.egg-info/PKG-INFO
src/vimpdb.egg-info/SOURCES.txt
src/vimpdb.egg-info/dependency_links.txt
src/vimpdb.egg-info/entry_points.txt
src/vimpdb.egg-info/not-zip-safe
src/vimpdb.egg-info/requires.txt
src/vimpdb.egg-info/top_level.txt
src/vimpdb/tests/__init__.py
src/vimpdb/tests/test_config.py
src/vimpdb/tests/test_proxy.py
src/vimpdb/tests/scripts/compatiblevim.py
src/vimpdb/tests/scripts/emptyserverlist.py
src/vimpdb/tests/scripts/incompatiblevim.py
src/vimpdb/tests/scripts/nopython.py
src/vimpdb/tests/scripts/noserver.py
src/vimpdb/tests/scripts/returncode.py
src/vimpdb/tests/scripts/rightserverlist.py
src/vimpdb/tests/scripts/wrongserverlist.py