Metadata-Version: 1.0
Name: vimpdb
Version: 0.4.4
Summary: Vim and Pdb integration
Home-page: http://github.com/gotcha/vimpdb
Author: Godefroid Chapelle
Author-email: gotcha@bubblenet.be
License: MIT
Keywords: pdb vim
Platform: UNKNOWN
Classifier: Programming Language :: Python :: 2.4
Classifier: Programming Language :: Python :: 2.5
Classifier: Programming Language :: Python :: 2.6
Classifier: Programming Language :: Python :: 2.7
Classifier: Operating System :: MacOS :: MacOS X
Classifier: Operating System :: POSIX :: Linux
Classifier: Operating System :: Microsoft :: Windows
Classifier: Topic :: Software Development :: Debuggers
Classifier: Topic :: Text Editors
